{
  "code": 0,
  "msg": "",
  "count": 10,
  "data": [
    {
      "id": 10000,
      "title": "文章标题-0",
      "isComment": true,
      "isRecommendation": false,
      "isTop": false,
      "browseNum": 255,
      "commentNum": 24,
      "likeNum": 700,
      "createDate": "2019-03-30 12:39:56",
      "testFiled": 57
    },
    {
      "id": 10001,
      "title": "文章标题-1",
      "isComment": false,
      "isRecommendation": true,
      "isTop": false,
      "browseNum": 884,
      "commentNum": 58,
      "likeNum": 8690,
      "createDate": "2019-03-30 12:39:56",
      "testFiled": 27
    },
    {
      "id": 10002,
      "title": "文章标题-2",
      "isComment": true,
      "isRecommendation": false,
      "isTop": true,
      "browseNum": 650,
      "commentNum": 77,
      "likeNum": 8078,
      "createDate": "2019-03-30 12:39:56",
      "testFiled": 31
    },
    {
      "id": 10003,
      "title": "文章标题-3",
      "isComment": true,
      "isRecommendation": true,
      "isTop": false,
      "browseNum": 362,
      "commentNum": 157,
      "likeNum": 7017,
      "createDate": "2019-03-30 12:39:56",
      "testFiled": 68
    },
    {
      "id": 10004,
      "title": "文章标题-4",
      "isComment": false,
      "isRecommendation": true,
      "isTop": true,
      "browseNum": 807,
      "commentNum": 51,
      "likeNum": 3262,
      "createDate": "2019-03-30 12:39:56",
      "testFiled": 6
    }
  ]
}